{
  "/_app": "pages/_app.js",
  "/about-us-2": "pages/about-us-2.html",
  "/aboutPage": "pages/aboutPage.html",
  "/alternativelivelihoods": "pages/alternativelivelihoods.html",
  "/api/contactus": "pages/api/contactus.js",
  "/api/internshipApplicationForm": "pages/api/internshipApplicationForm.js",
  "/api/jobApplications/route": "pages/api/jobApplications/route.js",
  "/api/jobSubmission": "pages/api/jobSubmission.js",
  "/api/sendMail": "pages/api/sendMail.js",
  "/blank": "pages/blank.html",
  "/blog-details-2": "pages/blog-details-2.html",
  "/blog-grid-2": "pages/blog-grid-2.html",
  "/blog-large-left-sidebar": "pages/blog-large-left-sidebar.html",
  "/blog-large-right-sidebar": "pages/blog-large-right-sidebar.html",
  "/careers/[jobId]/apply": "pages/careers/[jobId]/apply.html",
  "/careers": "pages/careers.js",
  "/children": "pages/children.html",
  "/coming-soon": "pages/coming-soon.html",
  "/contact-us-2": "pages/contact-us-2.html",
  "/contactus": "pages/contactus.html",
  "/donations": "pages/donations.html",
  "/error-404": "pages/error-404.html",
  "/faq-2": "pages/faq-2.html",
  "/gallery": "pages/gallery.js",
  "/health": "pages/health.html",
  "/hiv-aids": "pages/hiv-aids.html",
  "/hivInterventionWork": "pages/hivInterventionWork.html",
  "/": "pages/index.html",
  "/internships": "pages/internships.html",
  "/ourResources": "pages/ourResources.html",
  "/ourstories/[id]": "pages/ourstories/[id].html",
  "/ourstories": "pages/ourstories.js",
  "/pricing-table-2": "pages/pricing-table-2.html",
  "/reports": "pages/reports.js",
  "/services-2": "pages/services-2.html",
  "/services-details-2": "pages/services-details-2.html",
  "/sitedown": "pages/sitedown.html",
  "/team-2": "pages/team-2.html",
  "/test": "pages/test.html",
  "/test2": "pages/test2.html",
  "/volunteer": "pages/volunteer.html",
  "/wishlistPage": "pages/wishlistPage.html",
  "/_error": "pages/_error.js",
  "/_document": "pages/_document.js",
  "/404": "pages/404.html"
}